smith_tea_calendar/__init__.py
smith_tea_calendar/__main__.py
smith_tea_calendar/scraper.py
smith_tea_calendar-0.1.3.dist-info/WHEEL
smith_tea_calendar-0.1.3.dist-info/entry_points.txt
smith_tea_calendar-0.1.3.dist-info/METADATA
smith_tea_calendar-0.1.3.dist-info/RECORD
