Metadata-Version: 2.3
Name: smith-tea-calendar
Version: 0.1.3
Summary: Create an iCal file containing upcoming Smith Tea subscription renewals
Requires-Dist: click>=8.3.1
Requires-Dist: ical>=12.1.2
Requires-Dist: playwright>=1.57.0
Requires-Python: >=3.14
